shipzo_mult/__init__.py
shipzo_mult/shipzo_mult.py
shipzo_mult-0.1.3.dist-info/METADATA
shipzo_mult-0.1.3.dist-info/WHEEL
shipzo_mult-0.1.3.dist-info/entry_points.txt
shipzo_mult-0.1.3.dist-info/top_level.txt
shipzo_mult-0.1.3.dist-info/RECORD
