Metadata-Version: 2.1
Name: shipzo_mult
Version: 0.1.3
Summary: Default template for PDM package
Author-email: rlaehgus97 <starkim625@gmail.com>
License: MIT
Project-URL: Homepage, https://github.com/rlaehgus97/shipzo_mult
Project-URL: Issues, https://github.com/rlaehgus97/shipzo_mult/issues
Requires-Python: >=3.9
